pydantic_dict/__init__.py
pydantic_dict/_sentinel.py
pydantic_dict/_utils.py
pydantic_dict/base_model_dictionary.py
pydantic_dict/exceptions.py
pydantic_dict-0.0.3.dist-info/LICENSE
pydantic_dict-0.0.3.dist-info/METADATA
pydantic_dict-0.0.3.dist-info/WHEEL
pydantic_dict-0.0.3.dist-info/top_level.txt
pydantic_dict-0.0.3.dist-info/RECORD
