Metadata-Version: 2.1
Name: pydantic-dict
Version: 0.0.3
Summary: A pydantic model subclass that implements Python's dictionary interface.
Author-email: Austin Raney <aaraney@protonmail.com>
License: MIT License
Keywords: pydantic,serialization,deserialization,json
Classifier: Development Status :: 3 - Alpha
Classifier: Intended Audience :: Developers
Classifier: License :: OSI Approved :: MIT License
Classifier: Operating System :: Microsoft :: Windows
Classifier: Operating System :: Unix
Classifier: Programming Language :: Python :: 3.7
Classifier: Programming Language :: Python :: 3.8
Classifier: Programming Language :: Python :: 3.9
Classifier: Programming Language :: Python :: 3.10
Classifier: Programming Language :: Python :: 3.11
Classifier: Topic :: Utilities
Requires-Python: >=3.7
License-File: LICENSE
Requires-Dist: pydantic (<2)
Requires-Dist: typing-extensions
Provides-Extra: dev
Requires-Dist: black ; extra == 'dev'
Provides-Extra: test
Requires-Dist: pytest (>=7.0.0) ; extra == 'test'
